{
  "#Status_MainMenu": "Im Men端",
  "#status_LevelSelect": "Die Wahl eine Ebene",
  "#status_Spring": "Spiele im Fr端hjahr",
  "#status_Fall": "Spiele im Herbst",
  "#status_Winter": "Spiele im Winter",
  "#status_Spring_TimeAttack": "Spielen Fr端hling in der Zeit Challenge-Modus",
  "#status_Fall_TimeAttack": "Spielen Herbst in der Zeit Challenge-Modus",
  "#status_Winter_TimeAttack": "Spielen Winter in der Zeit Challenge-Modus",
  "#status_Spring_Hardcore": "Spielen Fr端hling in der Zeit Hardcore-Modus",
  "#status_Fall_Hardcore": "Spielen Herbst in der Zeit Hardcore-Modus",
  "#status_Winter_Hardcore": "Spielen Winter in der Zeit Hardcore-Modus"
}