{
  "#steam_dac_rp_findingmatch": "Spielsuche",
  "#steam_dac_rp_gm_classic": "Klassisch",
  "#steam_dac_rp_gm_duos": "Duo-Modus",
  "#steam_dac_rp_gm_normal": "Normale Partie",
  "#steam_dac_rp_gm_puzzle": "Puzzle",
  "#steam_dac_rp_gm_sandbox": "Freistil",
  "#steam_dac_rp_gm_streetfight": "Straßenkampf",
  "#steam_dac_rp_gm_turbo": "Knockout",
  "#steam_dac_rp_ingame_disconnected": "Im Spiel – Verbindung getrennt",
  "#steam_dac_rp_ingame_eliminated": "Eliminiert",
  "#steam_dac_rp_ingame_playingboring": "{%param2%} ({%param3%}): Im Spiel",
  "#steam_dac_rp_ingame_playingcitycrawl": "Stadttour – {%param3%}",
  "#steam_dac_rp_ingame_playingturbo": "{%param2%} ({%param3%}): Runde %param0%, %param1%",
  "#steam_dac_rp_ingame_playingunderlord": "{%param2%} ({%param3%}): Runde %param0%, %param1% LP",
  "#steam_dac_rp_ingame_spectator": "Schaut zu – Runde %param0%",
  "#steam_dac_rp_ingame_victory": "Spielende",
  "#steam_dac_rp_inparty": "Hauptmenü – Gruppe",
  "#steam_dac_rp_inprivategame_disconnected": "Privates Spiel – Verbindung getrennt",
  "#steam_dac_rp_inprivategame_eliminated": "Eliminiert",
  "#steam_dac_rp_inprivategame_spectator": "Schaut zu – Runde %param0%",
  "#steam_dac_rp_inprivategame_victory": "Spielende",
  "#steam_dac_rp_mainmenu": "Hauptmenü",
  "#steam_dac_rp_mm_casual": "Gelegenheitsspiel",
  "#steam_dac_rp_mm_privatelobby": "Privates Spiel",
  "#steam_dac_rp_mm_ranked": "Ranglistenspiel",
  "#steam_dac_rp_mm_solobot": "Lokal",
  "#steam_dac_rp_place_1": "1. Platz",
  "#steam_dac_rp_place_2": "2. Platz",
  "#steam_dac_rp_place_3": "3. Platz",
  "#steam_dac_rp_place_4": "4. Platz",
  "#steam_dac_rp_place_5": "5. Platz",
  "#steam_dac_rp_place_6": "6. Platz",
  "#steam_dac_rp_place_7": "7. Platz",
  "#steam_dac_rp_place_8": "8. Platz",
  "#steam_dac_rp_ul_0": "Kein Underlord",
  "#steam_dac_rp_ul_1": "Anessix",
  "#steam_dac_rp_ul_2": "Jull",
  "#steam_dac_rp_ul_3": "Enno",
  "#steam_dac_rp_ul_4": "Hobgen"
}