{
  "#rp_activity_flying_an_attack_chopper_in_heat": "Сеет хаос с веротолета",
  "#rp_activity_freefalling_from_great_height": "В свободном падении над Солисом",
  "#rp_dlc_premium_wingsuit": "Рассекает небо Солиса используя Skystriker",
  "#rp_exploring_biome_alpine": "Исследует снежные пики",
  "#rp_exploring_biome_desert": "Исследует иссушающие пустыни Солиса",
  "#rp_exploring_biome_grassland": "Исследует бескрайние зеленые луга",
  "#rp_exploring_biome_rainforest": "Исследует джунгли Ванай",
  "#rp_extreme_weather_in_blizzard": "Ослеплен бурей в горах",
  "#rp_extreme_weather_in_sandstorm": "Сражается с песчаной бурей в пустыне",
  "#rp_extreme_weather_in_tornado": "Заигрывает с торнадо",
  "#rp_extreme_weather_in_tropical_storm": "Уворачивается от молний в Ванай",
  "#rp_feat_0": "Смывается от Черной Руки",
  "#rp_feat_10": "Забирается на невероятную высоту в вингсьюте",
  "#rp_feat_11": "Слоняется по Солису",
  "#rp_feat_13": "Летит на самолете близко к земле",
  "#rp_feat_15": "Сеет хаос в море",
  "#rp_feat_17": "Рассекает по волнам вокруг Солиса",
  "#rp_feat_18": "Носится на лодке... по суше",
  "#rp_feat_1e": "Сеет хаос с веротолета",
  "#rp_feat_27": "Демонстрирует Черной Руке ветропушку",
  "#rp_feat_28": "Показывает ускоритель Черной Руке",
  "#rp_feat_2a": "Сбрасывает ящики... на Черную Руку",
  "#rp_feat_4": "Показывает солдатам Черной Руки днище машины",
  "#rp_feat_5": "Катается на лодке... по суше",
  "#rp_feat_8": "Водит как гонщик — быстро и аккуратно",
  "#rp_feat_9": "В свободном падении над Солисом",
  "#rp_feat_a": "Парасейлинг в Солисе",
  "#rp_feat_f": "Летит в вингсьюте в торнадо",
  "#rp_mission_1aaebcb2": "Проводит операцию Песчаное жало",
  "#rp_mission_23ddb383": "Добывает ионную спираль",
  "#rp_mission_43bffc69": "Проводит операцию Громобаржа",
  "#rp_mission_60f27079": "Исследует сеть Иллапа",
  "#rp_mission_792d7fac": "Проводит операцию Белая мгла",
  "#rp_mission_984258bd": "Проводит отвлекающий маневр в Нуэва Воз",
  "#rp_mission_a79212b3": "Исследует сигнал бедствия Агентства",
  "#rp_mission_ba016284": "Проводит операцию Танцующий с ветром",
  "#rp_mission_c82bd3ed": "На доставке со старым другом",
  "#rp_mission_d00d6d59": "Строит Ловца бурь",
  "#rp_mission_e8502044": "Встречается с Ланцой Моралесом",
  "#rp_mission_efcdd067": "Проводит операцию Иллапа",
  "#rp_mission_f7d213cc": "Грабит поезд",
  "#rp_mission_f941dd65": "Слушает теорию Цезаря",
  "#rp_quest_19be83dc": "Встречается с Сарженто в тылу",
  "#rp_quest_1ccda557": "Учит тайны истории Солиса",
  "#rp_quest_263954f2": "Занимается специальной доставкой",
  "#rp_quest_361e7634": "Ищет затерянную гробницу Оторонго",
  "#rp_quest_381ef60d": "Громит тарелки",
  "#rp_quest_41a3a3cf": "Открывает гробницу мудреца",
  "#rp_quest_4434dbbe": "Защищает место аварии в кратере",
  "#rp_quest_5696ff7d": "Расследует активность дронов",
  "#rp_quest_575c8d78": "Открывает гробницы трех детей",
  "#rp_quest_5fa1fa88": "Занимается контрразведкой",
  "#rp_quest_64ce714a": "Занимается защитой моста",
  "#rp_quest_65ee3ac6": "Едет вдоль священной реки",
  "#rp_quest_76442e47": "Занимается бомбардировкой",
  "#rp_quest_8a6a285": "Ездит в Алмазе под солнцем",
  "#rp_quest_8ef4d30d": "Открывает гробницу супруги",
  "#rp_quest_9954a06b": "Открывает гробницу воина",
  "#rp_quest_9dcfb2c9": "Развивает навыки общения",
  "#rp_quest_b2558a7c": "ВАНЕССА-А-А!",
  "#rp_quest_b7f234f": "Преследует джаггернаут Эксманна",
  "#rp_quest_b81d380a": "Ищет и уничтожает с новобранцами",
  "#rp_quest_c4638acf": "Проходит тренировку Пиньята",
  "#rp_quest_c6edb414": "В погоне за большими шишками",
  "#rp_quest_d2de8d37": "На кривой дорожке",
  "#rp_quest_e9b86ea2": "Помогает уничтожить береговой плацдарм",
  "#rp_quest_eac63cc3": "Становится новой звездой Гарланд Кинг",
  "#rp_quest_efae6cf2": "Помогает Гарланд Кинг с монтажом",
  "#rp_quest_efb18230": "Добывает информацию с новобранцами",
  "#rp_quest_f2bc55b5": "Открывает гробницу принцессы",
  "#rp_quest_f675de29": "В погоне за Цветком заката",
  "#rp_quest_fd64eb81": "Летает на вертолете",
  "#rp_strike_1677cc7f": "Ныряет в Пуэрто Диего",
  "#rp_strike_168600af": "Носится по Пуэрто Туллу",
  "#rp_strike_1f58e3b7": "Крадет корабль из Пуэрто Малага",
  "#rp_strike_20f6124": "Запускает ракеты с Охо де ла Прадера",
  "#rp_strike_26c0fce4": "Устраивает диверсию на Аэроспециаль",
  "#rp_strike_37edcf62": "Ныряет в Пуэрто Эспада",
  "#rp_strike_3fccc50d": "Ломает систему в аэропорту",
  "#rp_strike_4dc9e270": "Спускает воду в Муро Форталеза",
  "#rp_strike_538b6b13": "Запускает ракеты в Охо Дель Десерто",
  "#rp_strike_6e440a5c": "Вытаскивает призывников из Академии Ванай",
  "#rp_strike_8c2b6870": "Проводит налет на Просперо Роботика",
  "#rp_strike_9526ffeb": "Закрывает Мина Роканегра",
  "#rp_strike_a2378e95": "Атакует Просперо Балистика",
  "#rp_strike_a2b0bd62": "Загружает данные из Зоны Три",
  "#rp_strike_a35e1dcd": "Проникает на Мина Вендаваль",
  "#rp_strike_a4d3af93": "Захватывает воздушную базу Янакагуа",
  "#rp_strike_a70cdbe9": "Грабит «Просперо Танкес»",
  "#rp_strike_a7f37bb3": "Захватывает «Просперо Торретас»",
  "#rp_strike_b6bbc6f3": "Взламывает Приса Аутомовил",
  "#rp_strike_b8aab0c": "Вызволяет заключенных из Ла Мазморры",
  "#rp_strike_bb387961": "Сбегает из Адского лагеря",
  "#rp_strike_c19f1803": "Разносит ракеты в Охо де ла Джунгла",
  "#rp_strike_d7475f22": "Проникает на «Гранд Централ»",
  "#rp_strike_d9914877": "Нападает на Эстасьон Аталайя",
  "#rp_strike_de0544c1": "Обесточивает Просперо Астильеро",
  "#rp_strike_e716928e": "Выбирается из Академии Кача",
  "#rp_exploring_dlc1_island": "Изучение пустынного Исла Сантуарио",
  "#rp_quest_4e5c2524": "Выживает на Испытании Ла Ратонера",
  "#rp_quest_5820e054": "Участвует в гонке: Каминевадо",
  "#rp_quest_60553d14": "Участвует в гонке: Занесло так занесло",
  "#rp_quest_61fbec3c": "Участвует в беспределе: Петрол-сити",
  "#rp_quest_6d4b97ff": "Выживает в гонке: С молнией наперегонки",
  "#rp_quest_7f3bca6f": "Участвует в беспределе: Ралли на маяке",
  "#rp_quest_837d37cf": "Противостоит бандам на Испытании победой",
  "#rp_quest_87ca5db": "Участвует в гонке: Ночные мосты",
  "#rp_quest_92af9aff": "Участвует в беспределе: Испытание кубка богов",
  "#rp_quest_a0814e20": "Выживает в беспределе: Хаос на берегу",
  "#rp_quest_ae3986ff": "Выживает в гонке: Святое очищение",
  "#rp_quest_d4801636": "Участвует в беспределе: Зеленый округ",
  "#rp_quest_dc44835a": "Участвует в Испытании на Исла Интенса",
  "#rp_quest_e2c2297": "Противостоит бандам на Обряде посвящения",
  "#rp_quest_f813d4e6": "Исследование подполья Солиса"
}