{
  "#Activity_Conversation": "Traduciendo idiomas alienígenas",
  "#Activity_Farming": "Realizando exobotánica",
  "#Activity_ModeCreative": "Explorando sin límites",
  "#Activity_ModeNormal": "Trazando un universo infinito",
  "#Activity_ModeSurvival": "Trazando un universo infinito",
  "#Activity_ModePermadeath": "Trazando un universo infinito",
  "#Activity_SpaceCombat": "Luchando entre las estrellas",
  "#Activity_Trading": "Realizando comercio interestelar",
  "#Location_Planet": "Inspeccionando un planeta",
  "#Location_Space": "Volando por el espacio exterior",
  "#Location_Storm": "Sobreviviendo en condiciones extremas"
}